[
    {
        "id": 1,
        "nome": "Enxada",
        "custo": "Ferramenta inicial",
        "ingredientes":"",
        "melhorias":"",
        "validado":""
        },
    {
        "id": 2,
        "nome": "Enxada de Cobre",
        "custo": "2 000 ouros",
        "ingredientes":"Barra de cobre (5)",
        "melhorias":"Aumenta a alcance máxima 3 blocos, em uma linha a sua frente."
    },
    {
        "id": 3,
        "nome": "Enxada de Aço",
        "custo": "5 000 ouros",
        "ingredientes":"Barra de ferro (5)",
        "melhorias":"Aumenta o alcance máximo para 5 blocos, em uma linha à sua frente"
    },
    {
        "id": 4,
        "nome": "Enxada de Ouro",
        "custo": "10 000 ouros",
        "ingredientes":"Barra de ouro (5)",
        "melhorias":"Aumenta o alcance máximo para uma área de 3x3 blocos, à sua frente"
    },
    {
        "id": 5,
        "nome": "Enxada de Irídio",
        "custo": "25 000 ouros",
        "ingredientes":"Barra de irídio (5)",
        "melhorias":"Aumenta o alcance máximo para uma área de 3x6 blocos, à sua frente"
    }
]